{
	"classtype": "kObjectclass",
	"internalversion": 5,
	"designtaskname": "Startup_Task",
	"cvardefs": [
		{
			"name": "ccInPassword",
			"order": 8,
			"type": "kCharacter",
			"subtype": "kSimplechar",
			"sublen": 100000000
		},
		{
			"name": "ccInServer",
			"order": 9,
			"type": "kCharacter",
			"subtype": "kSimplechar",
			"sublen": 100000000
		},
		{
			"name": "ccInUsername",
			"order": 7,
			"type": "kCharacter",
			"subtype": "kSimplechar",
			"sublen": 100000000
		},
		{
			"name": "ccLastInitialisation",
			"order": 14,
			"type": "kCharacter",
			"subtype": "kSimplechar",
			"sublen": 15
		},
		{
			"name": "ccMailFromAddress",
			"order": 20,
			"type": "kCharacter",
			"subtype": "kSimplechar",
			"sublen": 100
		},
		{
			"name": "ccMailFromName",
			"order": 19,
			"type": "kCharacter",
			"subtype": "kSimplechar",
			"sublen": 100
		},
		{
			"name": "ccOutFrom",
			"order": 1,
			"type": "kCharacter",
			"subtype": "kSimplechar",
			"sublen": 100000000
		},
		{
			"name": "ccOutFromName",
			"order": 2,
			"type": "kCharacter",
			"subtype": "kSimplechar",
			"sublen": 100000000
		},
		{
			"name": "ccOutServer",
			"order": 3,
			"type": "kCharacter",
			"subtype": "kSimplechar",
			"sublen": 100000000
		},
		{
			"name": "ccPop3LoginName",
			"order": 10,
			"type": "kCharacter",
			"subtype": "kSimplechar",
			"sublen": 100
		},
		{
			"name": "ccSMTP_AuthenticationMethod",
			"order": 4,
			"type": "kCharacter",
			"subtype": "kSimplechar",
			"sublen": 100000000
		},
		{
			"name": "ccSMTP_ID",
			"order": 5,
			"type": "kCharacter",
			"subtype": "kSimplechar",
			"sublen": 100
		},
		{
			"name": "ccSMTP_PASSWORD",
			"order": 6,
			"type": "kCharacter",
			"subtype": "kSimplechar",
			"sublen": 100
		},
		{
			"name": "cInBuffer",
			"order": 12,
			"type": "kList",
			"subtype": "",
			"sublen": 0
		},
		{
			"name": "clFromCache",
			"order": 15,
			"type": "kList",
			"subtype": "",
			"sublen": 0
		},
		{
			"name": "clOutBuffer",
			"order": 11,
			"type": "kList",
			"subtype": "",
			"sublen": 0
		},
		{
			"name": "clStaticBCC",
			"order": 18,
			"type": "kList",
			"subtype": "",
			"sublen": 0
		},
		{
			"name": "clStaticCC",
			"order": 17,
			"type": "kList",
			"subtype": "",
			"sublen": 0
		},
		{
			"name": "clStaticTo",
			"order": 16,
			"type": "kList",
			"subtype": "",
			"sublen": 0
		},
		{
			"name": "cnSecure",
			"order": 13,
			"type": "kInteger",
			"subtype": "kShortint",
			"sublen": 0
		}
	],
	"ivardefs": [
		{
			"name": "ibAttachedFileJustWrittenWithPDFwriter",
			"order": 4,
			"type": "kBoolean",
			"subtype": 0,
			"sublen": 0,
			"initval": "kFalse"
		},
		{
			"name": "ibInitialised",
			"order": 31,
			"type": "kBoolean",
			"subtype": 0,
			"sublen": 0,
			"initval": "kFalse"
		},
		{
			"name": "ibVerifyCertificate",
			"order": 5,
			"type": "kBoolean",
			"subtype": 0,
			"sublen": 0
		},
		{
			"name": "icEmailProtocolStatus",
			"order": 27,
			"type": "kCharacter",
			"subtype": "kSimplechar",
			"sublen": 100000000
		},
		{
			"name": "iInBody",
			"order": 21,
			"type": "kCharacter",
			"subtype": "kSimplechar",
			"sublen": 100000000
		},
		{
			"name": "iInDate",
			"order": 18,
			"type": "kCharacter",
			"subtype": "kSimplechar",
			"sublen": 100000000
		},
		{
			"name": "iInEnclosureList",
			"order": 22,
			"type": "kList",
			"subtype": "",
			"sublen": 0
		},
		{
			"name": "iInFrom",
			"order": 19,
			"type": "kCharacter",
			"subtype": "kSimplechar",
			"sublen": 100000000
		},
		{
			"name": "iInPriority",
			"order": 17,
			"type": "kCharacter",
			"subtype": "kSimplechar",
			"sublen": 100000000
		},
		{
			"name": "iInReturnPath",
			"order": 8,
			"type": "kCharacter",
			"subtype": "kSimplechar",
			"sublen": 100000000
		},
		{
			"name": "iInSubject",
			"order": 20,
			"type": "kCharacter",
			"subtype": "kSimplechar",
			"sublen": 100000000
		},
		{
			"name": "ioErrors",
			"order": 3,
			"type": "kObject",
			"subtype": "oErrorsWeb",
			"sublen": 0
		},
		{
			"name": "ioReadXML",
			"order": 2,
			"type": "kObject",
			"subtype": "oReadXML",
			"sublen": 0
		},
		{
			"name": "iOutBCCAddressList",
			"order": 14,
			"type": "kList",
			"subtype": "",
			"sublen": 0
		},
		{
			"name": "iOutBody",
			"order": 12,
			"type": "kCharacter",
			"subtype": "kSimplechar",
			"sublen": 100000000
		},
		{
			"name": "iOutCCAddressList",
			"order": 13,
			"type": "kList",
			"subtype": "",
			"sublen": 0
		},
		{
			"name": "iOutEnclosureList",
			"order": 23,
			"type": "kList",
			"subtype": "",
			"sublen": 0
		},
		{
			"name": "iOutPriority",
			"order": 16,
			"type": "kInteger",
			"subtype": "kShortint",
			"sublen": 0
		},
		{
			"name": "iOutStatusCall",
			"order": 15,
			"type": "kCharacter",
			"subtype": "kSimplechar",
			"sublen": 100000000
		},
		{
			"name": "iOutSubject",
			"order": 11,
			"type": "kCharacter",
			"subtype": "kSimplechar",
			"sublen": 100000000
		},
		{
			"name": "iOutToAddressList",
			"order": 10,
			"type": "kList",
			"subtype": "",
			"sublen": 0
		}
	],
	"properties": {
		"collectperformancedata": false,
		"componenticon": 2307,
		"componenttype": "kCompStoreHidden",
		"createdate": "2017-07-19 20:13:07",
		"desc": "",
		"editor": "",
		"editordata": "",
		"external": true,
		"issupercomponent": false,
		"moddate": "2017-08-11 14:27:48",
		"selfcontained": false,
		"showascheckedout": false,
		"userinfo": "",
		"version": "2"
	}
}
