[
	{
		"name": "$event",
		"ident": 0,
		"order": 16384,
		"pvardefs": [

		],
		"lvardefs": [
			{
				"name": "lcJSON",
				"order": 1,
				"type": "kCharacter",
				"subtype": "kSimplechar",
				"sublen": 100000000
			},
			{
				"name": "lcMessage",
				"order": 3,
				"type": "kCharacter",
				"subtype": "kSimplechar",
				"sublen": 100000000
			},
			{
				"name": "lcTitle",
				"order": 4,
				"type": "kCharacter",
				"subtype": "kSimplechar",
				"sublen": 100000000,
				"initval": "'Validation Failed'"
			},
			{
				"name": "lrJSON",
				"order": 2,
				"type": "kRow",
				"subtype": "",
				"sublen": 0
			}
		]
	}
]
