{
	"classtype": "kTable",
	"internalversion": 3,
	"superclass": "tMasterApp",
	"designtaskname": "Startup_Task",
	"cvardefs": [

	],
	"ivardefs": [
		{
			"name": "___ROW1",
			"order": 1,
			"type": "kRow",
			"subtype": "",
			"sublen": 0
		},
		{
			"name": "___ROW2",
			"order": 2,
			"type": "kRow",
			"subtype": "",
			"sublen": 0
		}
	],
	"properties": {
		"collectperformancedata": false,
		"componenticon": 0,
		"componenttype": "kCompStoreHidden",
		"createdate": "2017-05-03 12:02:20",
		"desc": "",
		"editor": "",
		"editordata": "",
		"external": true,
		"issupercomponent": false,
		"moddate": "2015-04-30 09:55:19",
		"showascheckedout": false,
		"sqlclassname": "ssysAsyncEmails",
		"userinfo": "",
		"version": "2"
	}
}
